{
  "create": {
    "actors": [
      "pivotal",
      "prbpoint"
    ],
    "groups": [
      "admins",
      "clients",
      "users"
    ]
  },
  "read": {
    "actors": [
      "pivotal",
      "prbpoint"
    ],
    "groups": [
      "admins",
      "clients",
      "users"
    ]
  },
  "update": {
    "actors": [
      "pivotal",
      "prbpoint"
    ],
    "groups": [
      "admins",
      "users"
    ]
  },
  "delete": {
    "actors": [
      "pivotal",
      "prbpoint"
    ],
    "groups": [
      "admins",
      "users"
    ]
  },
  "grant": {
    "actors": [
      "pivotal",
      "prbpoint"
    ],
    "groups": [
      "admins"
    ]
  }
}